vev/__init__.py
vev/server_py2.py
vev/server_py3.py
vev/vev.py
vev-0.5.0.dist-info/DESCRIPTION.rst
vev-0.5.0.dist-info/METADATA
vev-0.5.0.dist-info/metadata.json
vev-0.5.0.dist-info/RECORD
vev-0.5.0.dist-info/top_level.txt
vev-0.5.0.dist-info/WHEEL
vev-0.5.0.dist-info/zip-safe
