Metadata-Version: 1.1
Name: vev
Version: 0.5.0
Summary: Simple HTTP server request routing
Home-page: https://github.com/cslarsen/vev
Author: Christian Stigen Larsen
Author-email: csl@csl.name
License: https://www.gnu.org/licenses/lgpl-2.1.html
Download-URL: https://github.com/cslarsen/vev/tarball/v0.5.0
Keywords: web,http,routing,server,url
Platform: unix
Platform: linux
Platform: osx
Platform: cygwin
Platform: win32
Classifier: Development Status :: 3 - Alpha
Classifier: Natural Language :: English
Classifier: Operating System :: MacOS :: MacOS X
Classifier: Operating System :: POSIX
Classifier: Operating System :: Unix
Classifier: Programming Language :: Python :: 2
Classifier: Programming Language :: Python :: 3
Classifier: Programming Language :: Python
